{
  "type": "object",
  "description": "Command to create a new job via the event bus",
  "properties": {
    "correlationId": {
      "type": "string"
    },
    "_userId": {
      "type": "string",
      "description": "Authenticated user's DID, injected by the /bus/emit gateway. Clients do not set this."
    },
    "jobType": {
      "type": "string",
      "enum": [
        "reference-annotation",
        "highlight-annotation",
        "assessment-annotation",
        "comment-annotation",
        "tag-annotation",
        "generation"
      ]
    },
    "resourceId": {
      "type": "string"
    },
    "params": {
      "type": "object",
      "additionalProperties": true
    }
  },
  "required": [
    "correlationId",
    "jobType",
    "resourceId",
    "params"
  ]
}
